CHANGELOG.txt
LICENSE.txt
MANIFEST.in
README.txt
setup.py
fakelibraries/__init__.py
fakelibraries.egg-info/PKG-INFO
fakelibraries.egg-info/SOURCES.txt
fakelibraries.egg-info/dependency_links.txt
fakelibraries.egg-info/top_level.txt