Metadata-Version: 1.1
Name: fakelibraries
Version: 0.0.2
Summary: A basic fake data probvider for health care system
Home-page: UNKNOWN
Author: Health Data Research UK
Author-email: kabir.khan@hdruk.ac.uk
License: MIT
Keywords: fakedataprovider
Platform: UNKNOWN
Classifier: Development Status :: 5 - Production/Stable
Classifier: Intended Audience :: Education
Classifier: Operating System :: Microsoft :: Windows :: Windows 10
Classifier: License :: OSI Approved :: MIT License
Classifier: Programming Language :: Python :: 3
